{
    "solution": {
        "tour_1_1": 1,
        "tour_1_2": 0,
        "tour_1_3": 0,
        "tour_1_4": 0,
        "tour_1_5": 0,
        "tour_2_1": 0,
        "tour_2_2": 1,
        "tour_2_3": 0,
        "tour_2_4": 0,
        "tour_2_5": 0,
        "tour_3_1": 0,
        "tour_3_2": 0,
        "tour_3_3": 0,
        "tour_3_4": 1,
        "tour_3_5": 0,
        "tour_4_1": 0,
        "tour_4_2": 0,
        "tour_4_3": 1,
        "tour_4_4": 0,
        "tour_4_5": 0,
        "tour_5_1": 0,
        "tour_5_2": 0,
        "tour_5_3": 0,
        "tour_5_4": 0,
        "tour_5_5": 1
    },
    "energy": 32704.004
}